config/config.yaml
config/hosts.yaml.example
remote_terminal_mcp-1.2.1.dist-info/licenses/LICENSE
src/__init__.py
src/__main__.py
src/command_state.py
src/error_check_helper.py
src/hosts_manager.py
src/mcp_server.py
src/shared_state.py
src/batch/__init__.py
src/batch/batch_executor.py
src/batch/batch_helpers.py
src/batch/batch_parser.py
src/config/__init__.py
src/config/config.py
src/config/config_dataclasses.py
src/config/config_init.py
src/config/config_loader.py
src/database/__init__.py
src/database/database_batch.py
src/database/database_batch_execution.py
src/database/database_batch_queries.py
src/database/database_batch_scripts.py
src/database/database_commands.py
src/database/database_conversations.py
src/database/database_manager.py
src/database/database_recipes.py
src/database/database_servers.py
src/output/__init__.py
src/output/output_buffer.py
src/output/output_buffer_base.py
src/output/output_buffer_filtered.py
src/output/output_filter.py
src/output/output_filter_commands.py
src/output/output_filter_decision.py
src/output/output_formatter.py
src/prompt/__init__.py
src/prompt/prompt_detector.py
src/prompt/prompt_detector_checks.py
src/prompt/prompt_detector_pager.py
src/prompt/prompt_detector_patterns.py
src/ssh/__init__.py
src/ssh/ssh_commands.py
src/ssh/ssh_connection.py
src/ssh/ssh_io.py
src/ssh/ssh_manager.py
src/state/__init__.py
src/state/shared_state_conversation.py
src/state/shared_state_monitor.py
src/state/shared_state_transfer.py
src/static/terminal.css
src/static/terminal.js
src/static/transfer-panel.js
src/static/fragments/head.html
src/static/fragments/terminal_container.html
src/static/fragments/transfer_panel.html
src/static/vendor/xterm-addon-fit.js
src/static/vendor/xterm.css
src/static/vendor/xterm.js
src/tools/__init__.py
src/tools/decorators.py
src/tools/sftp_compression.py
src/tools/sftp_compression_download.py
src/tools/sftp_compression_tar.py
src/tools/sftp_compression_upload.py
src/tools/sftp_decisions.py
src/tools/sftp_progress.py
src/tools/sftp_transfer_compressed.py
remote_terminal_mcp-1.2.1.dist-info/METADATA
remote_terminal_mcp-1.2.1.dist-info/WHEEL
remote_terminal_mcp-1.2.1.dist-info/entry_points.txt
remote_terminal_mcp-1.2.1.dist-info/top_level.txt
remote_terminal_mcp-1.2.1.dist-info/RECORD
