Metadata-Version: 2.4
Name: remote-terminal-mcp
Version: 1.2.1
Summary: Full SSH terminal for Linux servers with AI/user control and dual-stream visibility
Author-email: Tim <tim00r@github.com>
License-Expression: MIT
Project-URL: Homepage, https://github.com/TiM00R/remote-terminal
Project-URL: Repository, https://github.com/TiM00R/remote-terminal
Project-URL: Documentation, https://github.com/TiM00R/remote-terminal/tree/master/docs
Keywords: mcp,model-context-protocol,ssh,remote-terminal,linux,server-management,automation,devops,claude,ai
Classifier: Development Status :: 4 - Beta
Classifier: Intended Audience :: Developers
Classifier: Intended Audience :: System Administrators
Classifier: Operating System :: OS Independent
Classifier: Programming Language :: Python :: 3
Classifier: Programming Language :: Python :: 3.8
Classifier: Programming Language :: Python :: 3.9
Classifier: Programming Language :: Python :: 3.10
Classifier: Programming Language :: Python :: 3.11
Classifier: Programming Language :: Python :: 3.12
Classifier: Topic :: Software Development :: Libraries :: Python Modules
Classifier: Topic :: System :: Systems Administration
Classifier: Topic :: Terminals
Requires-Python: >=3.8
License-File: LICENSE
Requires-Dist: nicegui>=1.4.0
Requires-Dist: paramiko>=3.0.0
Requires-Dist: pyyaml>=6.0
Requires-Dist: python-dotenv>=1.0.0
Requires-Dist: aiofiles>=23.0.0
Requires-Dist: python-json-logger>=2.0.0
Requires-Dist: mcp>=1.0.0
Requires-Dist: starlette>=0.27.0
Requires-Dist: uvicorn>=0.23.0
Provides-Extra: dev
Requires-Dist: pytest>=7.0.0; extra == "dev"
Requires-Dist: black>=23.0.0; extra == "dev"
Requires-Dist: flake8>=6.0.0; extra == "dev"
Dynamic: license-file
